rr/__init__.py
rr/__main__.py
rr/process.py
rr/watcher.py
rr-0.2.0.dist-info/DESCRIPTION.rst
rr-0.2.0.dist-info/METADATA
rr-0.2.0.dist-info/RECORD
rr-0.2.0.dist-info/WHEEL
rr-0.2.0.dist-info/entry_points.txt
rr-0.2.0.dist-info/metadata.json
rr-0.2.0.dist-info/top_level.txt
