Metadata-Version: 2.0
Name: rr
Version: 0.2.0
Summary: Runner-Reloader for development
Home-page: https://github.com/zzzsochi/rr
Author: Alexander Zelenyak
Author-email: zzz.sochi@gmail.com
License: UNKNOWN
Keywords: runner,reload,develop
Platform: UNKNOWN
Classifier: License :: OSI Approved :: BSD License
Classifier: Operating System :: POSIX
Classifier: Programming Language :: Python :: 3.4
Classifier: Programming Language :: Python :: 3.5
Requires-Dist: colorama
Requires-Dist: zini
